lsshipper/__init__.py
lsshipper/__main__.py
lsshipper/connection.py
lsshipper/database.py
lsshipper/file_handler.py
lsshipper/logfile.py
lsshipper/reader_aio.py
lsshipper/start.py
lsshipper/common/__init__.py
lsshipper/common/config.py
lsshipper/common/state.py
lsshipper/common/utils.py
lsshipper-0.1.dist-info/DESCRIPTION.rst
lsshipper-0.1.dist-info/METADATA
lsshipper-0.1.dist-info/RECORD
lsshipper-0.1.dist-info/WHEEL
lsshipper-0.1.dist-info/entry_points.txt
lsshipper-0.1.dist-info/metadata.json
lsshipper-0.1.dist-info/top_level.txt
tests/__init__.py
tests/conftest.py
tests/socket_server.py
tests/test_connection.py
tests/test_reader_aio.py
tests/lsshipper/__init__.py
tests/lsshipper/conftest.py
tests/lsshipper/socket_server.py
tests/lsshipper/test_connection.py
tests/lsshipper/test_reader_aio.py
