Metadata-Version: 2.0
Name: lsshipper
Version: 0.1
Summary: Very basic python logstash shipper
Home-page: https://github.com/stavinsky/lsshipper/archive/0.1.tar.gz
Author: Anton Stavinsky
Author-email: stavinsky@gmail.com
License: MIT
Keywords: logstash filebeat
Platform: UNKNOWN
Classifier: Development Status :: 3 - Alpha
Classifier: Topic :: Utilities
Classifier: License :: OSI Approved :: MIT License
Requires-Python: >=3.5
Requires-Dist: aiofiles (==0.3.1)
Requires-Dist: configobj (==5.0.6)
